[
    {
      "id": 0,
      "value": "default",
      "label": "Default",
      "color": "orange",
      "description": "A default label"
    },
    {
      "id": 1,
      "value": "economics",
      "label": "Economics",
      "color": "brown",
      "description": "Test description 1"
    },
    {
      "id": 2,
      "value": "introduction",
      "label": "Introduction",
      "color": "darkblue",
      "description": "Test description 2"
    },
    {
      "id": 3,
      "value": "brexit",
      "label": "Brexit",
      "color": "#FF5630",
      "description": ""
    },
    {
      "id": 4,
      "value": "conclusion",
      "label": "Conclusion",
      "color": "#FF8B00",
      "description": ""
    },
    {
      "id": 5,
      "value": "europe",
      "label": "Europe",
      "color": "#FFC400",
      "description": ""
    },
    {
      "id": 6,
      "value": "ritual",
      "label": "Ritual",
      "color": "#36B37E",
      "description": ""
    },
    {
      "id": 7,
      "value": "negotiation",
      "label": "Negotiation",
      "color": "#00875A",
      "description": ""
    },
    {
      "id": 8,
      "value": "computer vision",
      "label": "Computer vision",
      "color": "#253858",
      "description": ""
    },
    {
      "id": 9,
      "value": "open source",
      "label": "Open Source",
      "color": "#666666",
      "description": ""
    }
  ]